soda/__init__.py
soda-0.0.1.dist-info/LICENSE
soda-0.0.1.dist-info/METADATA
soda-0.0.1.dist-info/WHEEL
soda-0.0.1.dist-info/top_level.txt
soda-0.0.1.dist-info/RECORD
